alterx/__init__.py
alterx/app.py
alterx/findskel.py
alterx/main.py
alterx/utils.py
alterx/walkdir.py
alterx/html/__init__.py
alterx/html/__main__.py
alterx/json/__init__.py
alterx/json/__main__.py
alterx/toml/__init__.py
alterx/toml/__main__.py
alterx/xml/__init__.py
alterx/xml/__main__.py
alterx/xml/etree.py
alterx/yaml/__init__.py
alterx/yaml/__main__.py
alterx-0.0.4.dist-info/METADATA
alterx-0.0.4.dist-info/WHEEL
alterx-0.0.4.dist-info/top_level.txt
alterx-0.0.4.dist-info/RECORD
