Metadata-Version: 2.4
Name: alterx
Version: 0.0.4
Summary: A powerful file processing toolkit for batch transformations of HTML, JSON, TOML, XML, and YAML files
Author: Jet-Logic
Project-URL: Homepage, https://github.com/jet-logic/alterx
Project-URL: Documentation, https://github.com/jet-logic/alterx
Project-URL: Repository, https://github.com/jet-logic/alterx
Project-URL: Issues, https://github.com/jet-logic/alterx/issues
Project-URL: Changelog, https://github.com/jet-logic/alterx/releases
Keywords: html,json,toml,xml,yaml,transformation,processing,batch
Classifier: Development Status :: 4 - Beta
Classifier: Intended Audience :: Developers
Classifier: Intended Audience :: System Administrators
Classifier: Programming Language :: Python :: 3
Classifier: Topic :: Software Development :: Libraries :: Python Modules
Classifier: Topic :: Text Processing :: Markup :: HTML
Classifier: Topic :: Text Processing :: Markup :: XML
Classifier: Topic :: Utilities
Requires-Python: >=3.8
Requires-Dist: lxml>=4.9.0
Requires-Dist: tomlkit>=0.11.0
Requires-Dist: PyYAML>=6.0
Provides-Extra: dev
Requires-Dist: pytest>=7.0; extra == "dev"
Requires-Dist: pytest-cov>=4.0; extra == "dev"
Requires-Dist: black>=23.0; extra == "dev"
Requires-Dist: flake8>=6.0; extra == "dev"
Requires-Dist: mypy; extra == "dev"
